integration_tests/__init__.py
integration_tests/abnormal_state.json
integration_tests/acceptance.py
integration_tests/catalog.json
integration_tests/configured_catalog.json
integration_tests/invalid_config.json
integration_tests/sample_config.json
integration_tests/sample_state.json
source_faker/__init__.py
source_faker/airbyte_message_with_cached_json.py
source_faker/purchase_generator.py
source_faker/source.py
source_faker/spec.json
source_faker/streams.py
source_faker/user_generator.py
source_faker/utils.py
source_faker/record_data/products.json
source_faker/schemas/products.json
source_faker/schemas/purchases.json
source_faker/schemas/users.json
ab_test_source_faker-0.0.0.dist-info/METADATA
ab_test_source_faker-0.0.0.dist-info/WHEEL
ab_test_source_faker-0.0.0.dist-info/top_level.txt
ab_test_source_faker-0.0.0.dist-info/RECORD
